igwn_lldd_common/__init__.py
igwn_lldd_common/cli.py
igwn_lldd_common/crc.py
igwn_lldd_common/frame2kafka.py
igwn_lldd_common/framekafkaconsumer.py
igwn_lldd_common/framekafkaproducer.py
igwn_lldd_common/framelen.py
igwn_lldd_common/io.py
igwn_lldd_common/kafka2frame.py
igwn_lldd_common/log.py
igwn_lldd_common/messageparser.py
igwn_lldd_common/statustopic.py
igwn_lldd_common/utils.py
igwn_lldd_common/tests/__init__.py
igwn_lldd_common/tests/conftest.py
igwn_lldd_common/tests/test_cli.py
igwn_lldd_common/tests/test_crc.py
igwn_lldd_common/tests/test_entrypoints.py
igwn_lldd_common/tests/test_frame_inteface.py
igwn_lldd_common/tests/test_frame_inteface_multiple.py
igwn_lldd_common/tests/test_frame_kafka_fast_forward.py
igwn_lldd_common/tests/test_frame_kafka_single.py
igwn_lldd_common/tests/test_frame_length.py
igwn_lldd_common/tests/test_io.py
igwn_lldd_common/tests/test_message_parser.py
igwn_lldd_common/tests/test_status_updates.py
igwn_lldd_common/tests/test_utils.py
igwn_lldd_common/tests/__pycache__/__init__.cpython-310.pyc
igwn_lldd_common/tests/__pycache__/__init__.cpython-311.pyc
igwn_lldd_common/tests/__pycache__/conftest.cpython-311-pytest-7.4.3.pyc
igwn_lldd_common/tests/__pycache__/test_cli.cpython-310-pytest-7.3.2.pyc
igwn_lldd_common/tests/__pycache__/test_cli.cpython-311-pytest-7.3.1.pyc
igwn_lldd_common/tests/__pycache__/test_cli.cpython-311-pytest-7.4.3.pyc
igwn_lldd_common/tests/__pycache__/test_entrypoints.cpython-310-pytest-7.3.2.pyc
igwn_lldd_common/tests/__pycache__/test_entrypoints.cpython-311-pytest-7.3.1.pyc
igwn_lldd_common/tests/__pycache__/test_entrypoints.cpython-311-pytest-7.4.3.pyc
igwn_lldd_common/tests/__pycache__/test_frame_inteface.cpython-310-pytest-7.3.2.pyc
igwn_lldd_common/tests/__pycache__/test_frame_inteface.cpython-311-pytest-7.3.1.pyc
igwn_lldd_common/tests/__pycache__/test_frame_inteface.cpython-311-pytest-7.4.3.pyc
igwn_lldd_common/tests/__pycache__/test_frame_inteface_multiple.cpython-310-pytest-7.3.2.pyc
igwn_lldd_common-0.4.1.dist-info/licenses/LICENSE
igwn_lldd_common-0.4.1.dist-info/METADATA
igwn_lldd_common-0.4.1.dist-info/WHEEL
igwn_lldd_common-0.4.1.dist-info/entry_points.txt
igwn_lldd_common-0.4.1.dist-info/top_level.txt
igwn_lldd_common-0.4.1.dist-info/RECORD
